dsutilbox/__init__.py
dsutilbox/preprocessing.py
dsutilbox-0.1.1.dist-info/licenses/LICENSE
dsutilbox-0.1.1.dist-info/METADATA
dsutilbox-0.1.1.dist-info/WHEEL
dsutilbox-0.1.1.dist-info/top_level.txt
dsutilbox-0.1.1.dist-info/RECORD
