Metadata-Version: 2.4
Name: dsutilbox
Version: 0.1.1
Summary: Lightweight utilities for data science workflows
Author: Youxi Li
Requires-Python: >=3.8
License-File: LICENSE
Requires-Dist: pandas
Dynamic: license-file
